{
	"dialogue": [
		{
			"id": "Start",
			"character": "Guy",
			"text": "You sounded great during rehersal!"
		},
		{
			"text": "How are you feeling?"
		},
		{
			"character": "You",
			"text": "...like I can't breathe..."
		},
		{
			"text": "...[shake rate=20.0 level=5 connected=1]like I'm going to throw up[/shake]..."
		},
		{
			"text": "...[shake rate=20.0 level=5 connected=1]like I shouldn't be here[/shake]..."
		},
		{
			"character": "Guy",
			"text": "Yeah, I had a feeling you might be struggling."
		},
		{
			"text": "Why don't you practice some box-breathing?"
		},
		{
			"function": "end_dialogue"
		}
	]
}
